test/__init__.py
test/test_athena_dataset.py
test/mocks/__init__.py
test/mocks/mock_athena_connector.py
tf_data_athena/__init__.py
tf_data_athena/factory.py
tf_data_athena/aws_persistense/__init__.py
tf_data_athena/aws_persistense/athena_connector.py
tf_data_athena/aws_persistense/athena_dataset.py
tf_data_athena/aws_persistense/util_functions.py
tf_data_athena-1.0.1.dist-info/METADATA
tf_data_athena-1.0.1.dist-info/WHEEL
tf_data_athena-1.0.1.dist-info/top_level.txt
tf_data_athena-1.0.1.dist-info/RECORD
