Metadata-Version: 2.1
Name: tf-data-athena
Version: 1.0.1
Summary: An implementation of tf.data.Dataset for aws Athena
Home-page: https://github.com/andreclaudino/tf-data-athena
Author: André Claudino
Author-email: 
License: MIT
Platform: UNKNOWN
Classifier: License :: OSI Approved :: MIT License
Classifier: Programming Language :: Python :: 3
Classifier: Programming Language :: Python :: 3.7
Requires-Dist: tensorflow-datasets (==2.1.0)
Requires-Dist: tensorflow (==2.1.0)
Requires-Dist: boto3 (==1.12.17)
